netspresso_trainer/VERSION
netspresso_trainer/__init__.py
netspresso_trainer/evaluator_common.py
netspresso_trainer/evaluator_main.py
netspresso_trainer/inferencer_common.py
netspresso_trainer/inferencer_main.py
netspresso_trainer/trainer_common.py
netspresso_trainer/trainer_main.py
netspresso_trainer/dataloaders/__init__.py
netspresso_trainer/dataloaders/base.py
netspresso_trainer/dataloaders/builder.py
netspresso_trainer/dataloaders/classification.py
netspresso_trainer/dataloaders/detection.py
netspresso_trainer/dataloaders/pose_estimation.py
netspresso_trainer/dataloaders/registry.py
netspresso_trainer/dataloaders/segmentation.py
netspresso_trainer/dataloaders/augmentation/__init__.py
netspresso_trainer/dataloaders/augmentation/registry.py
netspresso_trainer/dataloaders/augmentation/transforms.py
netspresso_trainer/dataloaders/augmentation/custom/__init__.py
netspresso_trainer/dataloaders/augmentation/custom/image_proc.py
netspresso_trainer/dataloaders/augmentation/custom/mixing.py
netspresso_trainer/dataloaders/augmentation/custom/mosaic.py
netspresso_trainer/dataloaders/utils/__init__.py
netspresso_trainer/dataloaders/utils/collate_fn.py
netspresso_trainer/dataloaders/utils/constants.py
netspresso_trainer/dataloaders/utils/loader.py
netspresso_trainer/dataloaders/utils/misc.py
netspresso_trainer/dataloaders/utils/sampler.py
netspresso_trainer/loggers/__init__.py
netspresso_trainer/loggers/base.py
netspresso_trainer/loggers/builder.py
netspresso_trainer/loggers/image.py
netspresso_trainer/loggers/mlflow.py
netspresso_trainer/loggers/registry.py
netspresso_trainer/loggers/stdout.py
netspresso_trainer/loggers/tensorboard.py
netspresso_trainer/loggers/visualizer.py
netspresso_trainer/losses/__init__.py
netspresso_trainer/losses/builder.py
netspresso_trainer/losses/common.py
netspresso_trainer/losses/registry.py
netspresso_trainer/losses/classification/__init__.py
netspresso_trainer/losses/detection/__init__.py
netspresso_trainer/losses/detection/retinanet.py
netspresso_trainer-1.4.1.dist-info/LICENSE
netspresso_trainer-1.4.1.dist-info/METADATA
netspresso_trainer-1.4.1.dist-info/WHEEL
netspresso_trainer-1.4.1.dist-info/entry_points.txt
netspresso_trainer-1.4.1.dist-info/top_level.txt
netspresso_trainer-1.4.1.dist-info/RECORD
