Metadata-Version: 2.1
Name: netspresso-trainer
Version: 1.4.1
Summary: NetsPresso Python Package
Home-page: https://github.com/Nota-NetsPresso/netspresso-trainer
Author: NetsPresso
Author-email: netspresso@nota.ai
License: UNKNOWN
Platform: UNKNOWN
Classifier: Development Status :: 5 - Production/Stable
Classifier: Intended Audience :: Developers
Classifier: Intended Audience :: Science/Research
Classifier: Operating System :: OS Independent
Classifier: Programming Language :: Python :: 3.8
Classifier: Programming Language :: Python :: 3.9
Classifier: Programming Language :: Python :: 3.10
Classifier: Topic :: Scientific/Engineering :: Artificial Intelligence
Requires-Python: >=3.8
Requires-Dist: torch>=2.0.1
Requires-Dist: torchvision
Requires-Dist: onnx
Requires-Dist: onnxruntime
Requires-Dist: numpy
Requires-Dist: pillow
Requires-Dist: tqdm
Requires-Dist: omegaconf
Requires-Dist: opencv-python
Requires-Dist: tensorboard
Requires-Dist: fvcore
Requires-Dist: safetensors
Requires-Dist: loguru>=0.6.0
Requires-Dist: datasets
Requires-Dist: gradio==3.50.2
Requires-Dist: torch-tb-profiler
Requires-Dist: scipy
Requires-Dist: pandas
Requires-Dist: requests
